{"format_version":"1.12.0","minecraft:geometry":[{"description":{"identifier":"geometry.chiyu","texture_width":64,"texture_height":64,"visible_bounds_width":4,"visible_bounds_height":2.5,"visible_bounds_offset":[0,0.75,0]},"bones":[{"name":"chiyu","pivot":[0,-4,0]},{"name":"body","parent":"chiyu","pivot":[0,2.5,-1],"cubes":[{"origin":[-2.5,0,-4.5],"size":[5,5,7],"uv":[0,0]},{"origin":[2,4.5,-5],"size":[1,1,4],"pivot":[2.5,3,-3.5],"rotation":[0,22.5,0],"uv":[28,14]},{"origin":[2,2.5,-2],"size":[1,1,1],"pivot":[2.5,3,-3.5],"rotation":[0,22.5,0],"uv":[31,17]},{"origin":[2,1.5,-5],"size":[1,1,4],"pivot":[2.5,3,-3.5],"rotation":[0,22.5,0],"uv":[28,14]},{"origin":[2,3.5,-5],"size":[1,1,1],"pivot":[2.5,3,-3.5],"rotation":[0,22.5,0],"uv":[31,17]},{"origin":[-3,4.5,-5],"size":[1,1,4],"pivot":[-2.5,3,-3.5],"rotation":[0,-22.5,0],"uv":[28,14],"mirror":true},{"origin":[-3,3.5,-5],"size":[1,1,1],"pivot":[-2.5,3,-3.5],"rotation":[0,-22.5,0],"uv":[31,17],"mirror":true},{"origin":[-3,1.5,-5],"size":[1,1,4],"pivot":[-2.5,3,-3.5],"rotation":[0,-22.5,0],"uv":[28,14],"mirror":true},{"origin":[-3,2.5,-2],"size":[1,1,1],"pivot":[-2.5,3,-3.5],"rotation":[0,-22.5,0],"uv":[31,17],"mirror":true},{"origin":[0,3.25,-1.25],"size":[0,4,5],"inflate":0.02,"uv":[24,5]}]},{"name":"eyes","parent":"body","pivot":[0,3.5,-3],"cubes":[{"origin":[-3.325,2.5,-4],"size":[0,2,2],"inflate":0.02,"pivot":[-2.775,2.25,-2.75],"rotation":[0,-22.5,0],"uv":[0,0]},{"origin":[3.325,2.5,-4],"size":[0,2,2],"inflate":0.02,"pivot":[2.775,2.25,-2.75],"rotation":[0,22.5,0],"uv":[0,0],"mirror":true}]},{"name":"left_tail","parent":"body","pivot":[1,3.25,2.5],"cubes":[{"origin":[1,0.25,2.5],"size":[0,8,14],"uv":[0,0],"mirror":true}]},{"name":"right_tail","parent":"body","pivot":[-1,3.25,2.5],"cubes":[{"origin":[-1,0.25,2.5],"size":[0,8,14],"uv":[0,0]}]},{"name":"left_tail_2","parent":"body","pivot":[0.5,0.75,2.5],"cubes":[{"origin":[0.5,-1.75,2.5],"size":[0,5,6],"uv":[12,24],"mirror":true}]},{"name":"right_tail_2","parent":"body","pivot":[-0.5,0.75,2.5],"cubes":[{"origin":[-0.5,-1.75,2.5],"size":[0,5,6],"uv":[12,24]}]},{"name":"leftwing","parent":"body","pivot":[2.5,0.75,-1.75],"cubes":[{"origin":[2.5,0.75,-3.25],"size":[5,0,5],"inflate":0.02,"uv":[12,0]}]},{"name":"rightwing","parent":"body","pivot":[-2.5,0.75,-1.75],"cubes":[{"origin":[-7.5,0.75,-3.25],"size":[5,0,5],"inflate":0.02,"uv":[19,5]}]}]}]}